git_zap/__init__.py
git_zap/cli.py
git_zap-0.2.0.dist-info/METADATA
git_zap-0.2.0.dist-info/WHEEL
git_zap-0.2.0.dist-info/entry_points.txt
git_zap-0.2.0.dist-info/RECORD
