Metadata-Version: 2.4
Name: git-zap
Version: 0.2.0
Summary: Command line tool for quickly creating detached git worktree checkouts.
License: MIT
Requires-Python: >=3.12
Requires-Dist: click>=8.1
